{
  "name": "1SHS10-080035",
  "status": "active",
  "created_at": "2026-06-23T08:58:10.602662+00:00",
  "updated_at": "2026-06-23T08:58:10.602662+00:00",
  "total_unique_parts": 2,
  "total_qty": 2,
  "parts": [
    {
      "code": "SH0S11-080035",
      "qty": 1,
      "family": "Other",
      "parent_code": "SH0S10-080035",
      "variant_root": "SH0S10-080035",
      "urn": "urn:adsk.wipprod:dm.lineage:xgnUwEZzSVyMmmLyxjjFyg"
    },
    {
      "code": "SH0S12-080000",
      "qty": 1,
      "family": "Other",
      "parent_code": "SH0S10-080035",
      "variant_root": "SH0S10-080035",
      "urn": "urn:adsk.wipprod:dm.lineage:0zKN-EYKSAeeKy1IoC15Uw"
    },
    {
      "code": "1SHG00-080035",
      "qty": 0,
      "family": "Other",
      "is_wrapper": true,
      "variant_root": "1SHG00-080035"
    },
    {
      "code": "SH0S10-080035",
      "qty": 0,
      "family": "Other",
      "is_wrapper": true,
      "variant_root": "SH0S10-080035"
    }
  ]
}